LICENSE
README.md
pyproject.toml
setup.cfg
setup.py
src/yfoption/__init__.py
src/yfoption/__version__.py
src/yfoption/yfoption.py
src/yfoption.egg-info/PKG-INFO
src/yfoption.egg-info/SOURCES.txt
src/yfoption.egg-info/dependency_links.txt
src/yfoption.egg-info/requires.txt
src/yfoption.egg-info/top_level.txt