Metadata-Version: 2.1
Name: yfoption
Version: 0.0.1
Summary: The package fetch option data from yahoo finance.
Home-page: https://github.com/socbase/yfoption
Author: Socbase
Author-email: socbase.me@gmail.com
License: MIT
Project-URL: Bug Tracker, https://github.com/socbase/yfoption.git/issues
Platform: UNKNOWN
Classifier: License :: OSI Approved :: MIT License
Classifier: Programming Language :: Python
Classifier: Programming Language :: Python :: 3
Classifier: Programming Language :: Python :: 3.6
Classifier: Programming Language :: Python :: Implementation :: CPython
Classifier: Programming Language :: Python :: Implementation :: PyPy
Requires-Python: >=3.6.0
License-File: LICENSE
